mbodied_ai/__about__.py
mbodied_ai/__init__.py
mbodied_ai-0.0.1.dist-info/METADATA
mbodied_ai-0.0.1.dist-info/WHEEL
mbodied_ai-0.0.1.dist-info/licenses/LICENSE.txt
mbodied_ai-0.0.1.dist-info/RECORD
