Metadata-Version: 2.3
Name: mbodied-ai
Version: 0.0.1
Summary: Pydantic agents for interacting with various backends.
Project-URL: Documentation, https://github.com/mbodiai/mbodied#readme
Project-URL: Issues, https://github.com/mbodiai/mbodied/issues
Project-URL: Source, https://github.com/mbodiai/mbodied
Author-email: Mbodi AI <info@mbodi.ai>
License-Expression: Apache-2.0
License-File: LICENSE.txt
Classifier: Development Status :: 4 - Beta
Classifier: Programming Language :: Python
Classifier: Programming Language :: Python :: 3.8
Classifier: Programming Language :: Python :: 3.9
Classifier: Programming Language :: Python :: 3.10
Classifier: Programming Language :: Python :: 3.11
Classifier: Programming Language :: Python :: 3.12
Classifier: Programming Language :: Python :: Implementation :: CPython
Classifier: Programming Language :: Python :: Implementation :: PyPy
Requires-Python: >=3.8
